README.rst
setup.py
adapay_merchant/__init__.py
adapay_merchant.egg-info/PKG-INFO
adapay_merchant.egg-info/SOURCES.txt
adapay_merchant.egg-info/dependency_links.txt
adapay_merchant.egg-info/requires.txt
adapay_merchant.egg-info/top_level.txt
adapay_merchant/api/__init__.py
adapay_merchant/api/application.py
adapay_merchant/api/merchant_profile.py
adapay_merchant/api/merchant_user.py
adapay_merchant/api/pay_conf.py
adapay_merchant/api/public_key.pem
adapay_merchant/api/request_tools.py